overseerr/__init__.py
overseerr/api_client.py
overseerr/api_response.py
overseerr/configuration.py
overseerr/exceptions.py
overseerr/py.typed
overseerr/rest.py
overseerr/api/__init__.py
overseerr/api/auth_api.py
overseerr/api/collection_api.py
overseerr/api/issue_api.py
overseerr/api/media_api.py
overseerr/api/movies_api.py
overseerr/api/other_api.py
overseerr/api/person_api.py
overseerr/api/public_api.py
overseerr/api/request_api.py
overseerr/api/search_api.py
overseerr/api/service_api.py
overseerr/api/settings_api.py
overseerr/api/tmdb_api.py
overseerr/api/tv_api.py
overseerr/api/users_api.py
overseerr/models/__init__.py
overseerr/models/cast.py
overseerr/models/collection.py
overseerr/models/company.py
overseerr/models/create_auth_local_request.py
overseerr/models/create_auth_logout2_xx_response.py
overseerr/models/create_auth_plex_request.py
overseerr/models/create_auth_reset_password_by_guid_request.py
overseerr/models/create_auth_reset_password_request.py
overseerr/models/create_discover_add_request.py
overseerr/models/create_issue_comment_request.py
overseerr/models/create_issue_request.py
overseerr/models/create_jobs_schedule_request.py
overseerr/models/create_media_by_status_request.py
overseerr/models/create_plex_sync_request.py
overseerr/models/create_request_request.py
overseerr/models/create_request_request_seasons.py
overseerr/models/create_user_import_from_plex_request.py
overseerr/models/create_user_register_push_subscription_request.py
overseerr/models/create_user_request.py
overseerr/models/create_user_settings_main_request.py
overseerr/models/create_user_settings_password_request.py
overseerr/models/create_user_settings_permissions_request.py
overseerr/models/credit_cast.py
overseerr/models/credit_crew.py
overseerr/models/crew.py
overseerr/models/discord_settings.py
overseerr/models/discord_settings_options.py
overseerr/models/discover_slider.py
overseerr/models/episode.py
overseerr/models/external_ids.py
overseerr/models/genre.py
overseerr-1.0.2.dist-info/METADATA
overseerr-1.0.2.dist-info/WHEEL
overseerr-1.0.2.dist-info/top_level.txt
overseerr-1.0.2.dist-info/RECORD
