Metadata-Version: 2.4
Name: overseerr
Version: 1.0.2
Summary: Overseerr API
Home-page: 
Author: OpenAPI Generator community
Author-email: OpenAPI Generator Community <team@openapitools.org>
Project-URL: Repository, https://github.com/devopsarr/overseerr-py
Keywords: OpenAPI,OpenAPI-Generator,Overseerr API
Requires-Python: >=3.9
Requires-Dist: urllib3<3.0.0,>=2.1.0
Requires-Dist: python-dateutil>=2.8.2
Requires-Dist: pydantic>=2
Requires-Dist: typing-extensions>=4.7.1
Requires-Dist: lazy-imports<2,>=1
Dynamic: author
